README.md
setup.py
pclip/__init__.py
pclip/aoi.json
pclip/cli_aoi2json.py
pclip/cli_sorter.py
pclip/clip_download.py
pclip/clip_geojson.py
pclip/clip_idlist.py
pclip/clip_json.py
pclip/download.py
pclip/pclip.py
pclip/planet_quota.py
pclip.egg-info/PKG-INFO
pclip.egg-info/SOURCES.txt
pclip.egg-info/dependency_links.txt
pclip.egg-info/entry_points.txt
pclip.egg-info/requires.txt
pclip.egg-info/top_level.txt